docCLI/__init__.py
docCLI/core.py
docCLI/docs.py
docCLI/drive.py
docCLI/google.py
docCLI/mime.py
docCLI/sheets.py
docCLI/credentials/client_secret.json
docCLI-0.0.4.dist-info/DESCRIPTION.rst
docCLI-0.0.4.dist-info/METADATA
docCLI-0.0.4.dist-info/RECORD
docCLI-0.0.4.dist-info/WHEEL
docCLI-0.0.4.dist-info/entry_points.txt
docCLI-0.0.4.dist-info/metadata.json
docCLI-0.0.4.dist-info/top_level.txt
