Metadata-Version: 2.0
Name: docCLI
Version: 0.0.4
Summary: A command line interface for Google Docs suite
Home-page: https://github.com/asoderman/docCLI
Author: Alex Soderman
Author-email: asoderman.as@gmail.com
License: UNKNOWN
Platform: UNKNOWN
Requires-Dist: Click
Requires-Dist: google-api-python-client
